activation_pathway_analysis_backend/.gitignore
activation_pathway_analysis_backend/__init__.py
activation_pathway_analysis_backend/apalysis_tf.py
activation_pathway_analysis_backend/apalysis_torch.py
activation_pathway_analysis_backend/metrics.py
activation_pathway_analysis_backend/redis_cache.py
activation_pathway_analysis_backend/types.py
activation_pathway_analysis_backend/utils.py
activation_pathway_analysis_backend/utils_tf.py
activation_pathway_analysis_backend/utils_torch.py
apalysis-0.0.2.dist-info/METADATA
apalysis-0.0.2.dist-info/WHEEL
apalysis-0.0.2.dist-info/RECORD
