Metadata-Version: 2.1
Name: APalysis
Version: 0.0.2
Summary: 
Home-page: https://github.com/rahatzamancse/APalysis
Keywords: APalysis
Author: Rahat Zaman
Author-email: rahatzamancse@gmail.com
Requires-Python: >=3.10,<3.11
Classifier: Programming Language :: Python :: 3
Classifier: Programming Language :: Python :: 3.10
Requires-Dist: beartype (>=0.16.4,<0.17.0)
Requires-Dist: fastapi (>=0.108.0,<0.109.0)
Requires-Dist: grandalf (>=0.8,<0.9)
Requires-Dist: keract (>=4.5.1,<5.0.0)
Requires-Dist: matplotlib (>=3.8.2,<4.0.0)
Requires-Dist: nltk (>=3.8.1,<4.0.0)
Requires-Dist: nptyping (>=2.5.0,<3.0.0)
Requires-Dist: numpy (>=1.26.3,<2.0.0)
Requires-Dist: pillow (>=10.2.0,<11.0.0)
Requires-Dist: pydot (>=2.0.0,<3.0.0)
Requires-Dist: redis (>=5.0.1,<6.0.0)
Requires-Dist: scikit-learn (>=1.3.2,<2.0.0)
Requires-Dist: tensorflow (==2.15)
Requires-Dist: tensorflow-datasets (>=4.9.4,<5.0.0)
Requires-Dist: torch (>=2.1.2,<3.0.0)
Requires-Dist: torchvision (>=0.16.2,<0.17.0)
Requires-Dist: tqdm (>=4.66.1,<5.0.0)
Requires-Dist: uvicorn (>=0.25.0,<0.26.0)
Project-URL: Repository, https://github.com/rahatzamancse/APalysis
